pynotify/__init__.py
pynotify/apps.py
pynotify/config.py
pynotify/dispatchers.py
pynotify/exceptions.py
pynotify/handlers.py
pynotify/helpers.py
pynotify/models.py
pynotify/notify.py
pynotify/receivers.py
pynotify/serializers.py
pynotify/tasks.py
pynotify/locale/cs/LC_MESSAGES/django.mo
pynotify/locale/cs/LC_MESSAGES/django.po
pynotify/migrations/0001_initial.py
pynotify/migrations/0002_notification_extra_data.py
pynotify/migrations/0003_related_object_name_not_required.py
pynotify/migrations/0004_add_admin_template.py
pynotify/migrations/0005_adminnotificationtemplate_is_active.py
pynotify/migrations/0006_add_send_push.py
pynotify/migrations/0007_migration.py
pynotify/migrations/0008_migration.py
pynotify/migrations/0009_migration.py
pynotify/migrations/__init__.py
django_pynotify-0.5.5.dist-info/AUTHORS.rst
django_pynotify-0.5.5.dist-info/LICENSE
django_pynotify-0.5.5.dist-info/METADATA
django_pynotify-0.5.5.dist-info/WHEEL
django_pynotify-0.5.5.dist-info/top_level.txt
django_pynotify-0.5.5.dist-info/RECORD
