Metadata-Version: 1.2
Name: django-pynotify
Version: 0.5.5
Summary: General purpose notification library for Django
Home-page: https://github.com/druids/django-pynotify
Author: Ondřej Kulatý
Author-email: kulaty.o@gmail.com
License: MIT license
Keywords: django-pynotify
Platform: UNKNOWN
Classifier: Development Status :: 3 - Alpha
Classifier: Intended Audience :: Developers
Classifier: License :: OSI Approved :: MIT License
Classifier: Natural Language :: English
Classifier: Programming Language :: Python :: 3.6
Classifier: Programming Language :: Python :: 3.7
Classifier: Programming Language :: Python :: 3.8
Classifier: Programming Language :: Python :: 3.9
Classifier: Programming Language :: Python :: 3.10
Classifier: Programming Language :: Python :: 3.11
Requires-Python: >=3.6
